{
  "date": "2025-10-31",
  "lastUpdated": "2025-10-31T19:37:46.757498",
  "totalRecommendations": 20,
  "openPositions": 5,
  "recommendations": [
    {
      "rank": 1,
      "symbol": "GE",
      "confidence": 71.6,
      "predictedReturn": 2.56,
      "currentPrice": 310.99,
      "priceTimestamp": "2025-10-31T19:34:59.156594",
      "priceSource": "google_finance",
      "priceVerified": true,
      "gtcBuy": 295.77,
      "gtcSell": 340.44,
      "priceDiffPct": 5.1,
      "status": "WATCHING - Price 5.1% above buy target",
      "finalScore": 0.0183
    },
    {
      "rank": 2,
      "symbol": "VLO",
      "confidence": 73.1,
      "predictedReturn": 2.35,
      "currentPrice": 169.83,
      "priceTimestamp": "2025-10-31T19:35:10.111537",
      "priceSource": "google_finance",
      "priceVerified": true,
      "gtcBuy": 160.75,
      "gtcSell": 185.08,
      "priceDiffPct": 5.6,
      "status": "WATCHING - Price 5.6% above buy target",
      "finalScore": 0.0172
    },
    {
      "rank": 3,
      "symbol": "SPCE",
      "confidence": 73.8,
      "predictedReturn": 2.23,
      "currentPrice": 3.92,
      "priceTimestamp": "2025-10-31T19:35:20.339200",
      "priceSource": "google_finance",
      "priceVerified": true,
      "gtcBuy": 3.72,
      "gtcSell": 4.28,
      "priceDiffPct": 5.4,
      "status": "WATCHING - Price 5.4% above buy target",
      "finalScore": 0.0164
    },
    {
      "rank": 4,
      "symbol": "MS",
      "confidence": 81.5,
      "predictedReturn": 1.59,
      "currentPrice": 164.8,
      "priceTimestamp": "2025-10-31T19:35:30.942461",
      "priceSource": "google_finance",
      "priceVerified": true,
      "gtcBuy": 156.34,
      "gtcSell": 180.32,
      "priceDiffPct": 5.4,
      "status": "WATCHING - Price 5.4% above buy target",
      "finalScore": 0.013
    },
    {
      "rank": 5,
      "symbol": "DHR",
      "confidence": 67.9,
      "predictedReturn": 1.84,
      "currentPrice": 216.07,
      "priceTimestamp": "2025-10-31T19:35:41.534040",
      "priceSource": "google_finance",
      "priceVerified": true,
      "gtcBuy": 206.38,
      "gtcSell": 237.3,
      "priceDiffPct": 4.7,
      "status": "BUY_ZONE - Will execute if conditions met",
      "finalScore": 0.0125
    },
    {
      "rank": 6,
      "symbol": "MA",
      "confidence": 76.6,
      "predictedReturn": 1.6,
      "currentPrice": 554.43,
      "priceTimestamp": "2025-10-31T19:35:52.226868",
      "priceSource": "google_finance",
      "priceVerified": true,
      "gtcBuy": 522.42,
      "gtcSell": 601.93,
      "priceDiffPct": 6.1,
      "status": "WATCHING - Price 6.1% above buy target",
      "finalScore": 0.0122
    },
    {
      "rank": 7,
      "symbol": "HD",
      "confidence": 62.4,
      "predictedReturn": 1.85,
      "currentPrice": 379.85,
      "priceTimestamp": "2025-10-31T19:36:02.642240",
      "priceSource": "google_finance",
      "priceVerified": true,
      "gtcBuy": 363.84,
      "gtcSell": 407.23,
      "priceDiffPct": 4.4,
      "status": "BUY_ZONE - Will execute if conditions met",
      "finalScore": 0.0115
    },
    {
      "rank": 8,
      "symbol": "BBBY",
      "confidence": 83.8,
      "predictedReturn": 1.2,
      "currentPrice": 7.61,
      "priceTimestamp": "2025-10-31T19:36:13.299266",
      "priceSource": "google_finance",
      "priceVerified": true,
      "gtcBuy": 7.18,
      "gtcSell": 8.28,
      "priceDiffPct": 6.0,
      "status": "WATCHING - Price 6.0% above buy target",
      "finalScore": 0.0101
    },
    {
      "rank": 9,
      "symbol": "COST",
      "confidence": 72.3,
      "predictedReturn": 1.05,
      "currentPrice": 914.64,
      "priceTimestamp": "2025-10-31T19:36:17.935010",
      "priceSource": "google_finance",
      "priceVerified": true,
      "gtcBuy": 875.05,
      "gtcSell": 1007.34,
      "priceDiffPct": 4.5,
      "status": "BUY_ZONE - Will execute if conditions met",
      "finalScore": 0.0076
    },
    {
      "rank": 10,
      "symbol": "SNDL",
      "confidence": 74.4,
      "predictedReturn": 0.7,
      "currentPrice": 2.16,
      "priceTimestamp": "2025-10-31T19:36:22.506204",
      "priceSource": "google_finance",
      "priceVerified": true,
      "gtcBuy": 2.09,
      "gtcSell": 2.38,
      "priceDiffPct": 3.3,
      "status": "BUY_ZONE - Will execute if conditions met",
      "finalScore": 0.0052
    }
  ],
  "positions": [
    {
      "symbol": "COIN",
      "shares": 0.1,
      "entryPrice": 348.36,
      "currentPrice": 348.64,
      "profitPct": 0.08,
      "profitAmount": 0.03,
      "positionValue": 34.86,
      "entryDate": "2025-10-29",
      "status": "HELD"
    },
    {
      "symbol": "NVDA",
      "shares": 0.1422,
      "entryPrice": 207.3,
      "currentPrice": 204.1,
      "profitPct": -1.54,
      "profitAmount": -0.46,
      "positionValue": 29.02,
      "entryDate": "2025-10-29",
      "status": "HELD"
    },
    {
      "symbol": "PG",
      "shares": 0.16,
      "entryPrice": 152.49,
      "currentPrice": 151.03,
      "profitPct": -0.96,
      "profitAmount": -0.23,
      "positionValue": 24.16,
      "entryDate": "2025-10-27",
      "status": "HELD"
    },
    {
      "symbol": "HON",
      "shares": 0.1129,
      "entryPrice": 216.14,
      "currentPrice": 201.29,
      "profitPct": -6.87,
      "profitAmount": -1.68,
      "positionValue": 22.73,
      "entryDate": "2025-10-27",
      "status": "HELD"
    },
    {
      "symbol": "MMM",
      "shares": 0.1448,
      "entryPrice": 168.5,
      "currentPrice": 166.97,
      "profitPct": -0.91,
      "profitAmount": -0.22,
      "positionValue": 24.18,
      "entryDate": "2025-10-27",
      "status": "HELD"
    }
  ]
}