{
  "date": "2025-11-03",
  "lastUpdated": "2025-11-03T15:34:59.857033",
  "totalRecommendations": 0,
  "openPositions": 3,
  "recommendations": [],
  "positions": [
    {
      "symbol": "META",
      "shares": 0.3,
      "entryPrice": 660.77,
      "currentPrice": 647.46,
      "profitPct": -2.01,
      "profitAmount": -3.99,
      "positionValue": 194.24,
      "entryDate": "2025-11-03",
      "status": "HELD"
    },
    {
      "symbol": "AAPL",
      "shares": 1.0,
      "entryPrice": 266.87,
      "currentPrice": 268.18,
      "profitPct": 0.49,
      "profitAmount": 1.31,
      "positionValue": 268.18,
      "entryDate": "2025-11-03",
      "status": "HELD"
    },
    {
      "symbol": "NVDA",
      "shares": 0.3891,
      "entryPrice": 210.61,
      "currentPrice": 207.63,
      "profitPct": -1.41,
      "profitAmount": -1.16,
      "positionValue": 80.79,
      "entryDate": "2025-11-03",
      "status": "HELD"
    }
  ]
}